laniakea/__init__.py
laniakea/__main__.py
laniakea/__version__.py
laniakea/core/__init__.py
laniakea/core/common.py
laniakea/core/multipart.py
laniakea/core/userdata.py
laniakea/core/providers/__init__.py
laniakea/core/providers/azure/__init__.py
laniakea/core/providers/azure/manager.py
laniakea/core/providers/ec2/__init__.py
laniakea/core/providers/ec2/manager.py
laniakea/core/providers/gce/__init__.py
laniakea/core/providers/gce/manager.py
laniakea/core/providers/packet/__init__.py
laniakea/core/providers/packet/manager.py
laniakea/examples/amazon.json
laniakea/examples/azure.json
laniakea/examples/laniakea.json
laniakea/examples/packet.json
laniakea/userdata/ec2/common.sh
laniakea/userdata/ec2/default.sh
laniakea/userdata/ec2/funfuzz.sh
laniakea/userdata/gce/fuzzos.yml
laniakea/userdata/packet/default.sh
laniakea-1.17.1.dist-info/LICENSE
laniakea-1.17.1.dist-info/METADATA
laniakea-1.17.1.dist-info/WHEEL
laniakea-1.17.1.dist-info/entry_points.txt
laniakea-1.17.1.dist-info/top_level.txt
laniakea-1.17.1.dist-info/RECORD
