Metadata-Version: 2.1
Name: laniakea
Version: 1.17.1
Summary: Laniakea is a utility for managing instances at various cloud providers and aids in setting up a fuzzing cluster it can be used as a tool or as a library.
Home-page: https://github.com/MozillaSecurity/laniakea
Author: Christoph Diehl
Author-email: cdiehl@mozilla.com
Maintainer: Mozilla Fuzzing Team
Maintainer-email: fuzzing@mozilla.com
License: MPL 2.0
Project-URL: Bug Tracker, https://github.com/MozillaSecurity/laniakea/issues
Keywords: cluster packet ec2 azure fuzzing
Platform: UNKNOWN
Classifier: Intended Audience :: Developers
Classifier: Topic :: Software Development :: Testing
Classifier: Topic :: Security
Classifier: License :: OSI Approved :: Mozilla Public License 2.0 (MPL 2.0)
Classifier: Programming Language :: Python :: 2
Classifier: Programming Language :: Python :: 2.7
Classifier: Programming Language :: Python :: 3
Classifier: Programming Language :: Python :: 3.6
Requires-Dist: appdirs
Requires-Dist: azure-mgmt-resource (==1.2.2)
Requires-Dist: azure-common (==1.1.14)
Requires-Dist: boto (<3.0,>=2.48.0)
Requires-Dist: packet-python (==1.37.1)
Requires-Dist: apache-libcloud (==2.4.0)
Requires-Dist: pycryptodome (==3.7.3)
